multiomictree/__init__.py
multiomictree/common.py
multiomictree/multiomictree.py
multiomictree-0.0.2.dist-info/licenses/LICENSE
multiomictree-0.0.2.dist-info/METADATA
multiomictree-0.0.2.dist-info/WHEEL
multiomictree-0.0.2.dist-info/entry_points.txt
multiomictree-0.0.2.dist-info/top_level.txt
multiomictree-0.0.2.dist-info/RECORD
